oop_es/__init__.py
oop_es/aggregate.py
oop_es/event.py
oop_es/exception.py
oop_es/command/__init__.py
oop_es/command/command.py
oop_es/command/command_bus.py
oop_es/command/command_handler.py
oop_es/repository/__init__.py
oop_es/repository/aggregate_repository.py
oop_es/serializer/__init__.py
oop_es/serializer/event_serializer.py
oop_es/serializer/serializer.py
oop_es/store/__init__.py
oop_es/store/event_store.py
oop_es/store/exception.py
oop_es/store/in_memory_event_store.py
oop_es/test/__init__.py
oop_es/test/aggregate_test_case.py
oop_es/view/__init__.py
oop_es/view/projector.py
oop_es-0.3.0.dist-info/METADATA
oop_es-0.3.0.dist-info/WHEEL
oop_es-0.3.0.dist-info/top_level.txt
oop_es-0.3.0.dist-info/RECORD
