Metadata-Version: 2.4
Name: oop-es
Version: 0.3.0
Summary: OOP Event Sourcing package
Author: Volodymyr Chub
License: MIT
Project-URL: Homepage, https://github.com/ChubV/oop-es
Project-URL: Issues, https://github.com/ChubV/oop-es/issues
Provides-Extra: test
Requires-Dist: pytest; extra == "test"
Requires-Dist: pytest-asyncio; extra == "test"
Requires-Dist: ty; extra == "test"
Requires-Dist: ruff; extra == "test"
Provides-Extra: pg
Requires-Dist: oop-es-pg; extra == "pg"
